trio_future/__init__.py
trio_future/functions.py
trio_future/future.py
trio_future-0.1.1.dist-info/WHEEL
trio_future-0.1.1.dist-info/METADATA
trio_future-0.1.1.dist-info/RECORD
