Metadata-Version: 2.1
Name: trio-future
Version: 0.1.1
Summary: Capture the return values of concurrently executed trio functions
Home-page: https://github.com/danielhfrank/trio-future
License: MIT
Author: Dan Frank
Requires-Python: >=3.7,<4.0
Classifier: License :: OSI Approved :: MIT License
Classifier: Programming Language :: Python :: 3
Classifier: Programming Language :: Python :: 3.7
Classifier: Programming Language :: Python :: 3.8
Classifier: Programming Language :: Python :: 3.9
Requires-Dist: trio (>=0.17.0,<0.18.0)
Project-URL: Repository, https://github.com/danielhfrank/trio-future
